pyfortune/__init__.py
pyfortune/exception.py
pyfortune/session.py
py_fortune-0.9.4.dist-info/LICENSE
py_fortune-0.9.4.dist-info/METADATA
py_fortune-0.9.4.dist-info/WHEEL
py_fortune-0.9.4.dist-info/top_level.txt
py_fortune-0.9.4.dist-info/RECORD
